atsync/__init__.py
atsync/core.py
atsync-1.0.1.dist-info/METADATA
atsync-1.0.1.dist-info/RECORD
atsync-1.0.1.dist-info/WHEEL
atsync-1.0.1.dist-info/top_level.txt
